semantic_code_search/__init__.py
semantic_code_search/cli.py
semantic_code_search/cluster.py
semantic_code_search/embed.py
semantic_code_search/prompt.py
semantic_code_search/query.py
semantic_code_search-0.4.0.dist-info/LICENSE.txt
semantic_code_search-0.4.0.dist-info/METADATA
semantic_code_search-0.4.0.dist-info/WHEEL
semantic_code_search-0.4.0.dist-info/entry_points.txt
semantic_code_search-0.4.0.dist-info/top_level.txt
semantic_code_search-0.4.0.dist-info/RECORD
