Metadata-Version: 2.1
Name: semantic-code-search
Version: 0.4.0
Summary: Search your codebase with natural language.
Home-page: https://github.com/sturdy-dev/semantic-code-search
Author: Kiril Videlov
Author-email: kiril@codeball.ai
Keywords: semantic code search
Classifier: Development Status :: 3 - Alpha
Classifier: Environment :: Console
Classifier: Intended Audience :: Developers
Classifier: License :: OSI Approved :: GNU Affero General Public License v3
Classifier: Operating System :: OS Independent
Classifier: Programming Language :: Python :: 3
Classifier: Topic :: Software Development
Classifier: Topic :: Utilities
Requires-Python: >=3.8
License-File: LICENSE.txt
Requires-Dist: numpy (==1.22.4)
Requires-Dist: prompt-toolkit (==3.0.32)
Requires-Dist: Pygments (==2.12.0)
Requires-Dist: sentence-transformers (==2.2.2)
Requires-Dist: setuptools (==62.6.0)
Requires-Dist: torch (==1.12.1)
Requires-Dist: tree-sitter (==0.20.1)
Requires-Dist: tree-sitter-builds (==2022.8.27)
Requires-Dist: tree-sitter-languages (==1.5.0)
